ext/3f60354cf6dc5ac698bc9154163b4e6a/.git/HEAD
ext/3f60354cf6dc5ac698bc9154163b4e6a/.git/config
ext/3f60354cf6dc5ac698bc9154163b4e6a/.git/description
ext/3f60354cf6dc5ac698bc9154163b4e6a/.git/hooks/applypatch-msg.sample
ext/3f60354cf6dc5ac698bc9154163b4e6a/.git/hooks/commit-msg.sample
ext/3f60354cf6dc5ac698bc9154163b4e6a/.git/hooks/fsmonitor-watchman.sample
ext/3f60354cf6dc5ac698bc9154163b4e6a/.git/hooks/post-update.sample
ext/3f60354cf6dc5ac698bc9154163b4e6a/.git/hooks/pre-applypatch.sample
ext/3f60354cf6dc5ac698bc9154163b4e6a/.git/hooks/pre-commit.sample
ext/3f60354cf6dc5ac698bc9154163b4e6a/.git/hooks/pre-merge-commit.sample
ext/3f60354cf6dc5ac698bc9154163b4e6a/.git/hooks/pre-push.sample
ext/3f60354cf6dc5ac698bc9154163b4e6a/.git/hooks/pre-rebase.sample
ext/3f60354cf6dc5ac698bc9154163b4e6a/.git/hooks/pre-receive.sample
ext/3f60354cf6dc5ac698bc9154163b4e6a/.git/hooks/prepare-commit-msg.sample
ext/3f60354cf6dc5ac698bc9154163b4e6a/.git/hooks/push-to-checkout.sample
ext/3f60354cf6dc5ac698bc9154163b4e6a/.git/hooks/sendemail-validate.sample
ext/3f60354cf6dc5ac698bc9154163b4e6a/.git/hooks/update.sample
ext/3f60354cf6dc5ac698bc9154163b4e6a/.git/index
ext/3f60354cf6dc5ac698bc9154163b4e6a/.git/info/exclude
ext/3f60354cf6dc5ac698bc9154163b4e6a/.git/logs/HEAD
ext/3f60354cf6dc5ac698bc9154163b4e6a/.git/logs/refs/heads/main
ext/3f60354cf6dc5ac698bc9154163b4e6a/.git/logs/refs/remotes/origin/HEAD
ext/3f60354cf6dc5ac698bc9154163b4e6a/.git/objects/pack/pack-a1f943e0d94ea5c3fd7da3f23e53e1d6d9bfc98b.idx
ext/3f60354cf6dc5ac698bc9154163b4e6a/.git/objects/pack/pack-a1f943e0d94ea5c3fd7da3f23e53e1d6d9bfc98b.pack
ext/3f60354cf6dc5ac698bc9154163b4e6a/.git/objects/pack/pack-a1f943e0d94ea5c3fd7da3f23e53e1d6d9bfc98b.rev
ext/3f60354cf6dc5ac698bc9154163b4e6a/.git/packed-refs
ext/3f60354cf6dc5ac698bc9154163b4e6a/.git/refs/heads/main
ext/3f60354cf6dc5ac698bc9154163b4e6a/.git/refs/remotes/origin/HEAD
ext/3f60354cf6dc5ac698bc9154163b4e6a/testRegex.js
ext/__init__.py
ext/libs/bm25.py
ext/libs/bm25s.py
ragpipe-0.0.3.3.dist-info/LICENSE
ragpipe-0.0.3.3.dist-info/METADATA
ragpipe-0.0.3.3.dist-info/WHEEL
ragpipe-0.0.3.3.dist-info/RECORD
