Metadata-Version: 2.1
Name: ragpipe
Version: 0.0.3.3
Summary: ragpipe: iterate quickly on your RAG pipelines.
License: Apache 2.0
Author: Nishant Sinha
Author-email: nishant@offnote.co
Requires-Python: >=3.8.1,<3.13
Classifier: License :: Other/Proprietary License
Classifier: Programming Language :: Python :: 3
Classifier: Programming Language :: Python :: 3.9
Classifier: Programming Language :: Python :: 3.10
Classifier: Programming Language :: Python :: 3.11
Classifier: Programming Language :: Python :: 3.12
Provides-Extra: bm25ext
Provides-Extra: db
Requires-Dist: chromadb
Requires-Dist: docling
Requires-Dist: fastembed
Requires-Dist: jinja2
Requires-Dist: litellm
Requires-Dist: llama-index (>=0.10.7)
Requires-Dist: ollama
Requires-Dist: pdf2image
Requires-Dist: rank_bm25
Requires-Dist: safetensors
Requires-Dist: sentence-transformers
Requires-Dist: sympy
Requires-Dist: typer
